tarlister.py
tarlister-1.0.2.dist-info/METADATA
tarlister-1.0.2.dist-info/WHEEL
tarlister-1.0.2.dist-info/entry_points.txt
tarlister-1.0.2.dist-info/top_level.txt
tarlister-1.0.2.dist-info/RECORD
