Metadata-Version: 2.4
Name: tarlister
Version: 1.0.2
Summary: libarchive-based Tool for listing the entries in a archive file or tape
Project-URL: Homepage, https://github.com/marcusmueller/tarlister
Project-URL: Reason, https://unix.stackexchange.com/a/801135/106650
Requires-Python: >=3.10
Requires-Dist: libarchive-c
